RobotDeck/AssetLibrary.py
RobotDeck/AssetManager.py
RobotDeck/RobotDeck.py
RobotDeck/RobotDeck.pyproject
RobotDeck/RobotResource.qrc
RobotDeck/TestManager.py
RobotDeck/Theme.py
RobotDeck/Tools.py
RobotDeck/VirtualUserInterface.py
RobotDeck/__init__.py
RobotDeck/Interface/AssetManager.qml
RobotDeck/Interface/TestManager.qml
RobotDeck/Interface/Components/ThemedLabel.qml
RobotDeck/Interface/Scripts/Defines.js
robotdeck-0.0.1.dist-info/METADATA
robotdeck-0.0.1.dist-info/WHEEL
robotdeck-0.0.1.dist-info/licenses/LICENSE
robotdeck-0.0.1.dist-info/RECORD
